easyjailbreak/__init__.py
easyjailbreak/attacker/AutoDAN_Liu_2023.py
easyjailbreak/attacker/Cipher_Yuan_2023.py
easyjailbreak/attacker/CodeChameleon_2024.py
easyjailbreak/attacker/DeepInception_Li_2023.py
easyjailbreak/attacker/GCG_Zou_2023.py
easyjailbreak/attacker/Gptfuzzer_yu_2023.py
easyjailbreak/attacker/ICA_wei_2023.py
easyjailbreak/attacker/Jailbroken_wei_2023.py
easyjailbreak/attacker/MJP_Li_2023.py
easyjailbreak/attacker/Multilingual_Deng_2023.py
easyjailbreak/attacker/PAIR_chao_2023.py
easyjailbreak/attacker/ReNeLLM_ding_2023.py
easyjailbreak/attacker/TAP_Mehrotra_2023.py
easyjailbreak/attacker/__init__.py
easyjailbreak/attacker/attacker_base.py
easyjailbreak/constraint/ConstraintBase.py
easyjailbreak/constraint/DeleteHarmLess.py
easyjailbreak/constraint/DeleteOffTopic.py
easyjailbreak/constraint/PerplexityConstraint.py
easyjailbreak/constraint/__init__.py
easyjailbreak/datasets/__init__.py
easyjailbreak/datasets/instance.py
easyjailbreak/datasets/jailbreak_datasets.py
easyjailbreak/loggers/__init__.py
easyjailbreak/loggers/logger.py
easyjailbreak/metrics/__init__.py
easyjailbreak/metrics/Evaluator/Evaluator.py
easyjailbreak/metrics/Evaluator/Evaluator_ClassificationGetScore.py
easyjailbreak/metrics/Evaluator/Evaluator_ClassificationJudge.py
easyjailbreak/metrics/Evaluator/Evaluator_GenerativeGetScore.py
easyjailbreak/metrics/Evaluator/Evaluator_GenerativeJudge.py
easyjailbreak/metrics/Evaluator/Evaluator_Match.py
easyjailbreak/metrics/Evaluator/Evaluator_PatternJudge.py
easyjailbreak/metrics/Evaluator/Evaluator_PrefixExactMatch.py
easyjailbreak/metrics/Evaluator/__init__.py
easyjailbreak/metrics/Metric/__init__.py
easyjailbreak/metrics/Metric/metric.py
easyjailbreak/metrics/Metric/metric_ASR.py
easyjailbreak/metrics/Metric/metric_perplexit.py
easyjailbreak/models/__init__.py
easyjailbreak/models/huggingface_model.py
easyjailbreak/models/model_base.py
easyjailbreak/models/openai_model.py
easyjailbreak/models/wenxinyiyan_model.py
easyjailbreak-0.1.3.dist-info/LICENSE
easyjailbreak-0.1.3.dist-info/METADATA
easyjailbreak-0.1.3.dist-info/WHEEL
easyjailbreak-0.1.3.dist-info/top_level.txt
easyjailbreak-0.1.3.dist-info/RECORD
